flyweight2
