Metadata-Version: 1.2
Name: flyweight2
Version: 0.0.2
Summary: A variant of the Flyweight pattern that allows the object to be modified without affecting other objects, and automatically shares the memory if the modified object is the same as other objects
Home-page: https://github.com/jefffffrey/flyweight2
Author: Jeffrey
Author-email: Jeffrey.S.Teo@gmail.com
License: MIT
Keywords: flyweight,flyweight-pattern,objectpool,shared-memory
Platform: any
Classifier: Development Status :: 3 - Alpha
Classifier: Intended Audience :: Developers
Classifier: Topic :: Software Development :: Libraries
Classifier: Topic :: Software Development :: Libraries :: Python Modules
Classifier: License :: OSI Approved :: MIT License
Classifier: Operating System :: OS Independent
Classifier: Programming Language :: Python :: 2
Classifier: Programming Language :: Python :: 2.7
Requires-Python: ==2.7.*
